hashpic/__init__.py
hashpic/__main__.py
hashpic/blake2b.py
hashpic/config.py
hashpic/data.py
hashpic/game.py
hashpic/hashpic.py
hashpic/md5.py
hashpic/sha3.py
hashpic/sha512.py
hashpic/shake256.py
hashpic/test_util.py
hashpic/util.py
hashpic/whirlpool.py
hashpic-0.7.3.dist-info/LICENSE
hashpic-0.7.3.dist-info/METADATA
hashpic-0.7.3.dist-info/WHEEL
hashpic-0.7.3.dist-info/entry_points.txt
hashpic-0.7.3.dist-info/top_level.txt
hashpic-0.7.3.dist-info/RECORD
