Metadata-Version: 2.1
Name: hashpic
Version: 0.7.3
Summary: Create an image from a MD5, SHA512, SHA3-512, Blake2b or SHAKE256 hash
Home-page: https://github.com/0xflotus/hashpic
Author: 0xflotus
Author-email: 0xflotus+pypi@gmail.com
License: MIT
Platform: UNKNOWN
Classifier: License :: OSI Approved :: MIT License
Classifier: Programming Language :: Python :: 3
Classifier: Programming Language :: Python :: 3.9
License-File: LICENSE
Requires-Dist: argparse
Requires-Dist: Pillow
